anychange/__init__.py
anychange/main.py
anychange/py.typed
anychange/watcher.py
anychange-0.2.0.dist-info/METADATA
anychange-0.2.0.dist-info/WHEEL
anychange-0.2.0.dist-info/licenses/LICENSE
anychange-0.2.0.dist-info/RECORD
